decore/__init__.py
decore/models.py
decore/signals.py
django_ease-0.1.dist-info/METADATA
django_ease-0.1.dist-info/WHEEL
django_ease-0.1.dist-info/top_level.txt
django_ease-0.1.dist-info/RECORD
