Metadata-Version: 2.1
Name: django-ease
Version: 0.1
Summary: Contains all the abstract models, utils, decorators, etc that will be used in django development
Home-page: https://github.com/pypa/sampleproject
Author: satheesh Kumar
Author-email: satheesh.101097@gmail.com
License: UNKNOWN
Keywords: Djano Easy,decore
Platform: UNKNOWN
Classifier: Development Status :: 3 - Alpha
Classifier: Intended Audience :: Developers
Classifier: Topic :: Software Development :: Build Tools
Classifier: License :: OSI Approved :: MIT License
Classifier: Programming Language :: Python :: 3
Classifier: Programming Language :: Python :: 3.5
Classifier: Programming Language :: Python :: 3.6
Classifier: Programming Language :: Python :: 3.7
Classifier: Programming Language :: Python :: 3.8
Classifier: Programming Language :: Python :: 3 :: Only
Requires-Python: >=3.5, <4
Requires-Dist: Django (==3.1)
